{"kts": -2323161412778154674, "sum": "코빗에서는 실전 투자리그 시즌2 23주차 상금 지급 대상자를 발표했습니다. 상금은 2024년 9월 2일부터 9월 8일까지의 기간에 대해 지급되며, 중복으로 상금을 받을 수 있습니다. 상금은 정보 수집, 고객 확인, 계좌 연동을 완료한 회원에게만 지급됩니다. 또한, 실전 투자리그는 메이커 거래 리그와 투자 수익률 리그로 운영되며, 주간 매도 합산 금액이 10만원 이상인 회원만 순위에 집계됩니다. 상금은 매주 금요일에 지급되며, 제세공과금 22%가 공제됩니다.언제나 투자자 보호를 위해 노력하는 코빗이 되겠습니다.\n\n", "dat": 20240909, "ttl": "[안내] 코빗 실전 투자리그 시즌2 23주차 상금 지급 대상자 안내", "sid": "코빗-공지사항-공지", "url": "https://lightning.korbit.co.kr/notice/?noticeId=4ccE0KnbhaTfzE6wSFYSw9&page=1", "tgs": ["#금융소식요약봇", "#금융소식요약봇_코빗", "#금융소식요약봇_코빗_공지사항", "#금융소식요약봇_코빗_공지사항_공지"], "tmp": 1725872681689}