{"kts": -4612687248163360647, "sum": "❤ 첨부파일 : \"(금융위)240925(보도자료) 영업을 종료한 가상자산거래소의 이용자 자산을 차질없이 반환하겠습니다..pdf\"\n> 2024년 9월 26일, 금융위원회는 디지털자산보호재단 설립을 허가했다. 이 재단은 영업을 종료한 거래소의 이용자 자산을 반환하고, 안전하게 보관 및 관리할 예정이다. 재단은 은행 및 거래소와 협력하여 이용자 자산을 보호하고, 금융당국도 지원할 계획이다. 이를 통해 가상자산시장의 건전한 시장질서를 확립할 것으로 기대된다.\n", "dat": 20240925, "ttl": "[보도자료] 영업을 종료한 가상자산거래소의 이용자 자산을 차질없이 반환하겠습니다.. 금일 등록된 게시글", "sid": "금융위원회-금융정책-담당부서 : 가상자산과", "url": "https://www.fsc.go.kr/po010101/83127?srchCtgry=1&curPage=1&srchKey=&srchText=&srchBeginDt=&srchEndDt=", "tgs": ["#금융소식요약봇", "#금융소식요약봇_금융위원회", "#금융소식요약봇_금융위원회_금융정책", "#금융소식요약봇_금융위원회_금융정책_담당부서 : 가상자산과"], "tmp": 1727241040418}