{"kts": -5474425516757771092, "sum": "❤ 첨부파일 : \"240418(조간) 알펜시아 리조트 매각입찰 관련 부당한 공동행위 제재.pdf\"\n> 2024년 4월 17일, 강원도개발공사의 알펜시아 리조트 매각 입찰에서 담합한 6개 업체에 510억 400만원의 과징금 부과 및 검찰고발 결정. 공정위는 공공기관 자산매각 입찰에서의 담합행위 감시를 강화하고 엄정한 조치를 취할 예정. 이번 조치는 공정위가 담합에 가담한 사업자들을 엄정 제재한 첫 사례로 의의가 있다.\n", "dat": 20240417, "ttl": "강원도개발공사 발주 알펜시아리조트 자산 매각 입찰 관련 6개 사업자의 부당한 공동행위 제재", "sid": "공정거래위원회-공정위소식-보도-제조카르텔조사과", "url": "https://www.ftc.go.kr/www/selectReportUserView.do?key=10&rpttype=1&report_data_no=10555", "tgs": ["#금융소식요약봇", "#금융소식요약봇_공정거래위원회", "#금융소식요약봇_공정거래위원회_공정위소식", "#금융소식요약봇_공정거래위원회_공정위소식_보도", "#금융소식요약봇_공정거래위원회_공정위소식_보도_제조카르텔조사과"], "tmp": 1713323140636}