{"kts": -5725239346009518618, "sum": "❤ 첨부파일 : \"금융위원회 공고 제2024-198호(일반사무관리회사).pdf\"\n> 2024년 6월 12일, 금융위원회는 ㈜케이비펀드파트너스를 일반사무관리회사로 등록하였다. 해당 등록은 「자본시장과 금융투자업에 관한 법률」 제254조에 따라 이루어졌다.\n", "dat": 20240612, "ttl": "일반사무관리회사 신규 등록. 금일 등록된 게시글", "sid": "금융위원회-고시/공고/훈령-담당부서 : 자산운용과", "url": "https://www.fsc.go.kr/po040200/82425?srchCtgry=&curPage=1&srchKey=&srchText=&srchBeginDt=&srchEndDt=", "tgs": ["#금융소식요약봇", "#금융소식요약봇_금융위원회", "#금융소식요약봇_금융위원회_고시/공고/훈령", "#금융소식요약봇_금융위원회_고시/공고/훈령_담당부서 : 자산운용과"], "tmp": 1718152711750}