{"kts": -6637091903929652940, "sum": "❤ 첨부파일 : \"240430 (보도자료) 조간_’24년 1분기 등록 ABS 발행 실적.pdf\"\n> '24년 1분기에는 대출채권과 매출채권을 중심으로 ABS 발행이 증가했습니다. 특히 카드채권과 할부금융채권을 포함한 매출채권이 크게 증가했는데, 이는 전년대비 163.1% 증가한 것으로 나타났습니다. 또한 NPL 기초 ABS 발행도 증가했으며, 부동산 PF 기초 ABS 발행도 이전에는 없던 것이 등장했습니다. 이에 따라 등록 ABS 전체 발행 잔액은 전년대비 12.0% 증가한 것으로 나타났습니다.'\n", "dat": 20240429, "ttl": "’24년 1분기 등록 ABS 발행 실적", "sid": "금융감독원-보도자료-기업공시국", "url": "https://www.fss.or.kr/fss/bbs/B0000188/view.do?nttId=135657&menuNo=200218&pageIndex=1", "tgs": ["#금융소식요약봇", "#금융소식요약봇_금융감독원", "#금융소식요약봇_금융감독원_보도자료", "#금융소식요약봇_금융감독원_보도자료_기업공시국"], "tmp": 1714359870536}