{"kts": -7480812892630746548, "sum": "❤ 첨부파일 : \"(240718) “고용장려금， 줬다 다시 뺏다니”··· 코로나 기간에도 고령자 고용한 소상공인 “분노”(최종).pdf\"\n> 고령자 고용한 소상공인이 고령자 계속고용장려금 환수 문제로 분노. 국민권익위는 형식적 요건 외에 실질적 고용 여부 고려해야 함을 강조. 이미 지급된 지원금 환수는 부당하다고 판단하며 고용노동부에 환수 중지를 권고. 코로나 시기에 고령 근로자를 계속 고용한 사업주 보호를 요청.\n", "dat": 20240718, "ttl": "“고용장려금, 줬다 다시 뺏다니”··· 코로나 기간에도 고령자 고용한 소상공인 “..", "sid": "국민권익위원회-보도자료-복지노동민원과", "url": "https://www.acrc.go.kr/board.es?mid=a10402010000&bid=4A&act=view&list_no=74979&tag=&nPage=1", "tgs": ["#금융소식요약봇", "#금융소식요약봇_국민권익위원회", "#금융소식요약봇_국민권익위원회_보도자료", "#금융소식요약봇_국민권익위원회_보도자료_복지노동민원과"], "tmp": 1721279611634}