{"kts": -7573877690889639177, "sum": "❤ 첨부파일 : \"0513(14석간, 13일(월) 10시엠바고)투자유치과, 영국 에드워드 사(社), 극자외선(EUV)노광 공정용 핵심부품 생산공장 준공.pdf\"\n> 2024년 5월 14일, 영국 에드워드 사가 한국에 극자외선 노광 공정용 핵심부품 생산공장을 준공했다. 이를 통해 반도체 제조 공정용 진공펌프 생산 분야에서 세계 1위 기업으로 성장하며 국내 및 해외 반도체 기업에 공급할 예정이다. 이로 인해 국내 부품 생산 경쟁력이 강화되고 반도체 초격차를 이루는 데 기여할 것으로 기대된다.\n", "dat": 20240514, "ttl": "영국 에드워드 사(社), 극자외선(EUV)노광 공정용 핵심부품 생산공장 준공", "sid": "산업통상자원부-보도참고자료-투자유치과", "url": "https://www.motie.go.kr/kor/article/ATCL3f49a5a8c/169042/view?", "tgs": ["#금융소식요약봇", "#금융소식요약봇_산업통상자원부", "#금융소식요약봇_산업통상자원부_보도참고자료", "#금융소식요약봇_산업통상자원부_보도참고자료_투자유치과"], "tmp": 1715648598201}