{"kts": -7576509779438409349, "sum": "❤ 첨부파일 : \"(240926) 막다른 초등학교 진입로... ‘후문과 승하차 구역 설치’ 대안 마련.pdf\"\n> 국민권익위는 양주시의 막다른 초등학교 진입로 문제를 해결하기 위해 후문과 승하차 구역을 설치하기로 결정했다. 이를 통해 학생들의 통학 안전을 보장하고 교통사고 예방을 위한 조치를 취할 것이다. 해당 조치는 2025년 3월 개교를 앞둔 푸른샘초등학교 인근 주민들의 요구에 따라 이루어졌으며, 국민권익위는 이를 신속히 이행해 달라고 관계기관에 당부했다.\n", "dat": 20240930, "ttl": "막다른 초등학교 진입로... ‘후문과 승하차 구역 설치’ 대안 마련", "sid": "국민권익위원회-보도자료-도시수자원민원과", "url": "https://www.acrc.go.kr/board.es?mid=a10402010000&bid=4A&act=view&list_no=79046&tag=&nPage=1", "tgs": ["#금융소식요약봇", "#금융소식요약봇_국민권익위원회", "#금융소식요약봇_국민권익위원회_보도자료", "#금융소식요약봇_국민권익위원회_보도자료_도시수자원민원과"], "tmp": 1727656761842}