{"kts": -7906688805927352209, "sum": "❤ 첨부파일 : \"(참고자료, 29일(월) 15시엠바고)중동아프리카통상과, 앙골라 주앙 로렌쑤 대통령 방한 계기, ｢한-앙골라 비즈니스 포럼｣ 열려.pdf\"\n> 2024년 4월 29일, 앙골라 대통령 방한을 계기로 '한-앙골라 비즈니스 포럼'이 열렸다. 양국 180여 경제계 인사가 참석하여 무역·투자, 신재생 에너지 등 다양한 분야에서 협력 방안을 논의했고, KOTRA-AIPEX 간 협력 양해각서(MOU)도 체결되었다. 이를 통해 양국 간 경제활동을 지원하는 기반이 마련되었고, 앙골라와의 새로운 경제협력 모멘텀을 확보했다.\n", "dat": 20240429, "ttl": "(참고자료)앙골라 주앙 로렌쑤 대통령 방한 계기, ｢한-앙골라 비즈니스 포럼｣ 열려", "sid": "산업통상자원부-보도참고자료-중동아프리카통상과", "url": "https://www.motie.go.kr/kor/article/ATCL3f49a5a8c/168983/view?", "tgs": ["#금융소식요약봇", "#금융소식요약봇_산업통상자원부", "#금융소식요약봇_산업통상자원부_보도참고자료", "#금융소식요약봇_산업통상자원부_보도참고자료_중동아프리카통상과"], "tmp": 1714374152741}