{"kts": -854726761849036919, "sum": "❤ 첨부파일 : \"[2024-235] 금융위원회 공고-현대카드㈜.pdf\"\n> 현대카드가 '24.6.28에 신용점수 올리기 서비스를 위해 데이터 판매 및 중개 부수업무를 신고했다. 해당 업무는 「신용정보의 이용 및 보호에 관한 법률」에 따라 공고되었다.\n", "dat": 20240705, "ttl": "부수업무 신고 사실 공고 - 현대카드(주). 금일 등록된 게시글", "sid": "금융위원회-고시/공고/훈령-담당부서 : 금융데이터정책과", "url": "https://www.fsc.go.kr/po040200/82619?srchCtgry=&curPage=1&srchKey=&srchText=&srchBeginDt=&srchEndDt=", "tgs": ["#금융소식요약봇", "#금융소식요약봇_금융위원회", "#금융소식요약봇_금융위원회_고시/공고/훈령", "#금융소식요약봇_금융위원회_고시/공고/훈령_담당부서 : 금융데이터정책과"], "tmp": 1720154464850}