{"kts": 1820706764604947724, "sum": "❤ 첨부파일 : \"(240718) 국민권익위， 부패공익신고자에게 올해 2분기 보상금 10억9천만원 지급(최종).pdf\"\n> 국민권익위는 올해 2분기에 부패‧공익신고자에게 10억9천만원의 보상금을 지급했고, 산업, 고용, 연구개발, 복지 분야에서 보상금이 높았다. 다양한 분야에서 부정수급 사례가 발견되었으며, 추가 보상금이 지급되었다. 국민권익위는 신고자들의 용기를 칭찬하며 앞으로도 신고를 활성화하기 위해 노력할 것이라고 밝혔다.\n", "dat": 20240718, "ttl": "국민권익위, 부패‧공익신고자에게 올해 2분기 보상금 10억9천만원 지급", "sid": "국민권익위원회-보도자료-신고자보상과", "url": "https://www.acrc.go.kr/board.es?mid=a10402010000&bid=4A&act=view&list_no=74978&tag=&nPage=1", "tgs": ["#금융소식요약봇", "#금융소식요약봇_국민권익위원회", "#금융소식요약봇_국민권익위원회_보도자료", "#금융소식요약봇_국민권익위원회_보도자료_신고자보상과"], "tmp": 1721279646338}