{"kts": 2584727398596649127, "sum": "❤ 첨부파일 : \"240726(참고) 2024년 2분기 다단계판매업자 주요정보 변경사항 공개.pdf\"\n> 2024년 2분기 다단계판매업 업체 122개 중 신규 4건, 폐업 2건, 등록말소 1건, 정보 변경 9건 발생. 주요 변경사항은 한국특수판매공제조합과의 공제계약, 국민은행과의 채무 지급보증계약 등. 상호·주소·피해보상보험 변경 9건 중 2건은 최근 3년간 5회 이상 상호·주소 변경한 업체. 소비자는 업체 정보 확인하여 피해 예방 필요.\n", "dat": 20240726, "ttl": "2024년 2분기 다단계 판매업자 주요정보 변경사항 공개", "sid": "공정거래위원회-공정위소식-보도-특수거래정책과", "url": "https://www.ftc.go.kr/www/selectReportUserView.do?key=10&rpttype=1&report_data_no=10733", "tgs": ["#금융소식요약봇", "#금융소식요약봇_공정거래위원회", "#금융소식요약봇_공정거래위원회_공정위소식", "#금융소식요약봇_공정거래위원회_공정위소식_보도", "#금융소식요약봇_공정거래위원회_공정위소식_보도_특수거래정책과"], "tmp": 1721958398570}