{"kts": 3316753827243399098, "sum": "업비트에서는 렌더토큰(RENDER)의 리브랜딩 및 토큰 스왑이 완료되어 입출금 서비스를 재개합니다. 2024년 8월 16일 19:00 KST부터 RENDER 입출금이 가능하며, 기존 RNDR 입금 주소로의 입금은 불가능하니 새로운 주소를 이용해야 합니다. 최소 입금 수량은 0.1 RENDER이며, 출금 수수료는 0.01 RENDER입니다.언제나 회원님의 자산을 최우선으로 생각하는 업비트가 되겠습니다.\n\n", "dat": 20240816, "ttl": "렌더토큰(RENDER) 리브랜딩 및 토큰 스왑 완료에 따른 입출금 재개 안내", "sid": "업비트-공지사항-입출금", "url": "https://upbit.com/service_center/notice?id=4437", "tgs": ["#금융소식요약봇", "#금융소식요약봇_업비트", "#금융소식요약봇_업비트_공지사항", "#금융소식요약봇_업비트_공지사항_입출금"], "tmp": 1723802167142}