{"kts": 5041963586400518175, "sum": "❤ 첨부파일 : \"(240529) ‘응답하라! 2024 청춘신문고’ 대학 현장 찾아가 청년 민생 적극 해결!(최종).pdf\"\n> 국민권익위가 '응답하라! 2024 청춘신문고'를 통해 대학 현장에서 청년들의 고민을 듣고 해결 방안 모색. 대학 축제 기간에 한밭대, 연세대, 부산대를 방문하여 청년들의 의견 수렴. 학생들은 '국민신문고'를 통해 고민 발언 가능. 전문 조사관과 2030자문단이 고민 상담. 청년 취업부담 완화를 위해 외국어시험 유효기간 확대 및 채용기회 보장을 위한 제도 개선. 유철환 위원장은 청년의 목소리를 듣고 정부정책에 반영하겠다고 밝힘.\n", "dat": 20240529, "ttl": "‘응답하라! 2024 청춘신문고’ 대학 현장 찾아가 청년 민생 적극 해결!", "sid": "국민권익위원회-보도자료-홍보담당관", "url": "https://www.acrc.go.kr/board.es?mid=a10402010000&bid=4A&act=view&list_no=71323&tag=&nPage=1", "tgs": ["#금융소식요약봇", "#금융소식요약봇_국민권익위원회", "#금융소식요약봇_국민권익위원회_보도자료", "#금융소식요약봇_국민권익위원회_보도자료_홍보담당관"], "tmp": 1716942005504}