{"kts": 5720782497078078622, "sum": "❤ 첨부파일 : \"0530(31조간)기후에너지통상과, 중소기업 탄소국경조정제도 대응, 정부가 밀착 지원.pdf\"\n> 2024년 5월 30일, 중소기업 탄소국경조정제도 대응을 위해 정부가 밀착 지원하고 있음. 이를 위해 탄소국경조정제도 교육·연수 프로그램을 고도화하고, 수도권에 소재한 기업을 대상으로 정부 합동 설명회를 개최. 대응 우수기업의 경험을 공유하며 기업들의 이해와 지원을 강화하고 있음. 또한, 탄소중립 시대에 대비하여 기업의 탄소배출 측정 및 저감 역량 향상을 위한 지원을 앞으로도 계속할 예정임.\n", "dat": 20240530, "ttl": "중소기업 탄소국경조정제도 대응, 정부가 밀착 지원", "sid": "산업통상자원부-보도참고자료-기후에너지통상과", "url": "https://www.motie.go.kr/kor/article/ATCL3f49a5a8c/169127/view?", "tgs": ["#금융소식요약봇", "#금융소식요약봇_산업통상자원부", "#금융소식요약봇_산업통상자원부_보도참고자료", "#금융소식요약봇_산업통상자원부_보도참고자료_기후에너지통상과"], "tmp": 1717036740964}