{"kts": 6198260346934051132, "sum": "업비트는 2024년 4월 22일부로 '주문고도화' 기능을 전체 마켓에 지원한다. 최유리지정가 주문 유형과 IOC, FOK 주문 조건을 확인할 수 있으며, PC 웹과 모바일 앱에서 확인 가능하다. 주문고도화 기능은 업비트 PC웹과 모바일 앱 최신 버전을 통해 이용할 수 있으며, 안드로이드는 1.27.5 버전 이상, iOS는 1.27.6 버전부터 이용 가능하다. 주문고도화 관련 자세한 안내는 업비트 홈페이지에서 확인할 수 있다. 실험실 기능 사용 시 주의사항을 숙지해야 하며, 서비스 제공 안정성에 따라 변경될 수 있다. 실험실에서 제공 중인 서비스는 사전 안내 없이 중단될 수 있으며, 정식 출시되면 삭제될 수 있다.\n\n", "dat": 20240415, "ttl": "업비트 실험실 주문고도화(최유리지정가, IOC, FOK) 전체 마켓 대상 지원 안내 - (4/22 적용 예정)", "sid": "업비트-공지사항-안내", "url": "https://upbit.com/service_center/notice?id=4163", "tgs": ["#금융소식요약봇", "#금융소식요약봇_업비트", "#금융소식요약봇_업비트_공지사항", "#금융소식요약봇_업비트_공지사항_안내"], "tmp": 1713171760570}