{"kts": 8088816707124156951, "sum": "❤ 첨부파일 : \"240909 (보도자료) 금-핀 상호만남(Meet-up) 행사로 금융회사와 핀테크 기업간 협업을 촉진하겠습니다.hwp\"\n> 한국 금융위원회는 금융회사와 핀테크 기업 간 협업을 촉진하기 위해 제4회 \"금융회사-핀테크 기업 상호만남(Meet-Up)\" 행사를 개최했다. 이를 통해 협업을 추진하는 18개 핀테크 기업 중 1개 기업은 이미 테스트를 완료하고 상용화를 준비 중이며, 7개 기업은 테스트 중이다. 또한, 8개 핀테크 기업이 발표한 협업 제안은 음성인식, 보험, 데이터 분석 등의 다양한 분야에 걸쳐 있었다.\n", "dat": 20240909, "ttl": "금-핀 상호만남(Meet-up) 행사로 금융회사와 핀테크 기업간 협업을 촉진하겠습니다", "sid": "금융감독원-보도자료-디지털혁신국", "url": "https://www.fss.or.kr/fss/bbs/B0000188/view.do?nttId=138304&menuNo=200218&pageIndex=1", "tgs": ["#금융소식요약봇", "#금융소식요약봇_금융감독원", "#금융소식요약봇_금융감독원_보도자료", "#금융소식요약봇_금융감독원_보도자료_디지털혁신국"], "tmp": 1725859651370}