{"kts": 8625785277686198282, "sum": "❤ 첨부파일 : \"240717 (보도참고) 사업보고서 등에 대한 조사·감리결과 조치.hwp\"\n> 금융위원회 보도참고자료에 따르면, ㈜씨앗이 회계처리기준 위반으로 감사인지정 등의 조치를 받았습니다. 또한, 회계감사기준 위반으로 감사업무제한 등의 조치를 받았으며, 외부감사 방해로 과징금과 검찰고발을 받았습니다. 감사인과 공인회계사도 매출 관련 계정 감사절차 소홀로 감사업무제한과 과징금을 받았습니다.\n", "dat": 20240717, "ttl": "사업보고서 등에 대한 조사,감리결과 조치", "sid": "금융감독원-보도자료-회계감리1국", "url": "https://www.fss.or.kr/fss/bbs/B0000188/view.do?nttId=137220&menuNo=200218&pageIndex=1", "tgs": ["#금융소식요약봇", "#금융소식요약봇_금융감독원", "#금융소식요약봇_금융감독원_보도자료", "#금융소식요약봇_금융감독원_보도자료_회계감리1국"], "tmp": 1721217620763}