{"kts": 9197238887942376508, "sum": "❤ 첨부파일 : \"240423(설명) 점주단체 등록제 및 협의의무제 도입 가맹사업법 개정안 관련.pdf\"\n> 가맹사업법 개정안에 대한 공정거래위원회의 입장은 충분한 논의가 필요하며, 필수품목 거래조건 협의제를 우선 시행 후 점진적으로 접근해야 한다. 현재의 개정안은 가맹산업에 부정적 영향을 미칠 우려가 있으므로 정부부처와 이해관계자들과의 심도 깊은 논의가 필요하다. 공정거래위원회는 신중한 검토를 거쳐 입법을 지원하고 역할을 성실히 수행할 계획이다. (500 characters)\n", "dat": 20240423, "ttl": "점주단체 등록제 및 협의의무제 도입 가맹사업법 개정안 관련", "sid": "공정거래위원회-공정위소식-보도-가맹거래정책과", "url": "https://www.ftc.go.kr/www/selectReportUserView.do?key=10&rpttype=1&report_data_no=10572", "tgs": ["#금융소식요약봇", "#금융소식요약봇_공정거래위원회", "#금융소식요약봇_공정거래위원회_공정위소식", "#금융소식요약봇_공정거래위원회_공정위소식_보도", "#금융소식요약봇_공정거래위원회_공정위소식_보도_가맹거래정책과"], "tmp": 1713846225290}